asdparser/asd.py
asdparser/model.py
asdparser-0.4.2.dist-info/METADATA
asdparser-0.4.2.dist-info/WHEEL
asdparser-0.4.2.dist-info/licenses/LICENSE
asdparser-0.4.2.dist-info/RECORD
