Metadata-Version: 2.1
Name: ASDParser
Version: 0.4.2
Summary: A python parser for the ASD database
Project-URL: Homepage, https://github.com/pegerto/ASDParser
Project-URL: Bug Tracker, https://github.com/pegerto/ASDParser
Author-email: Pegerto Fernandez <pegerto@gmail.com>
License-File: LICENSE
Classifier: License :: OSI Approved :: MIT License
Classifier: Operating System :: OS Independent
Classifier: Programming Language :: Python :: 3
Classifier: Topic :: Scientific/Engineering
Classifier: Topic :: Scientific/Engineering :: Artificial Intelligence
Classifier: Topic :: Scientific/Engineering :: Bio-Informatics
Requires-Python: >=3.7
Requires-Dist: pandas>=2.0.0
Requires-Dist: untangle>=1.2.0
